LICENSE
README.md
setup.cfg
setup.py
./kiroframe_arcee/__init__.py
./kiroframe_arcee/arcee.py
./kiroframe_arcee/name_generator.py
./kiroframe_arcee/platform.py
./kiroframe_arcee/utils.py
./kiroframe_arcee/collectors/__init__.py
./kiroframe_arcee/collectors/command_line.py
./kiroframe_arcee/collectors/console.py
./kiroframe_arcee/collectors/git.py
./kiroframe_arcee/collectors/hardware.py
./kiroframe_arcee/collectors/module.py
./kiroframe_arcee/libs/__init__.py
./kiroframe_arcee/libs/GPUtil/GPUtil.py
./kiroframe_arcee/libs/GPUtil/__init__.py
./kiroframe_arcee/libs/GPUtil/demo_GPUtil.py
./kiroframe_arcee/modules/__init__.py
./kiroframe_arcee/modules/dataset.py
./kiroframe_arcee/modules/providers/__init__.py
./kiroframe_arcee/modules/providers/amazon.py
./kiroframe_arcee/modules/providers/local_file.py
./kiroframe_arcee/platforms_meta/__init__.py
./kiroframe_arcee/platforms_meta/azure.py
./kiroframe_arcee/sender/__init__.py
./kiroframe_arcee/sender/sender.py
kiroframe_arcee.egg-info/PKG-INFO
kiroframe_arcee.egg-info/SOURCES.txt
kiroframe_arcee.egg-info/dependency_links.txt
kiroframe_arcee.egg-info/requires.txt
kiroframe_arcee.egg-info/top_level.txt
tests/test_data.py
tests/test_platform.py