Metadata-Version: 2.4
Name: kiroframe_arcee
Version: 0.1.50
Summary: ML profiling tool for Kiroframe
Home-page: https://my.kiroframe.com/
Author: Hystax
License: "Apache License 2.0"
Project-URL: Source, https://github.com/hystax/kiroframe_arcee
Keywords: arcee,ml,kiroframe,finops,mlops
Requires-Python: <4,>=3.8
License-File: LICENSE
Requires-Dist: aiohttp==3.10.11
Requires-Dist: aiofiles==23.2.1
Requires-Dist: psutil==7.0.0
Requires-Dist: aioboto3==14.1.0
Dynamic: license-file
